readvideo/__init__.py
readvideo/cli.py
readvideo/core/__init__.py
readvideo/core/audio_processor.py
readvideo/core/transcript_fetcher.py
readvideo/core/whisper_wrapper.py
readvideo/platforms/__init__.py
readvideo/platforms/bilibili.py
readvideo/platforms/local.py
readvideo/platforms/youtube.py
readvideo/utils/__init__.py
readvideo-0.1.1.dist-info/WHEEL
readvideo-0.1.1.dist-info/entry_points.txt
readvideo-0.1.1.dist-info/METADATA
readvideo-0.1.1.dist-info/RECORD
