Metadata-Version: 2.3
Name: readvideo
Version: 0.1.1
Summary: A Python tool for downloading and transcribing videos from YouTube/Bilibili and local media files
Keywords: video,transcription,youtube,bilibili,audio,whisper
Author: Jiahao Luo
Author-email: Jiahao Luo <luoshitou9@gmail.com>
License: MIT
Classifier: Development Status :: 4 - Beta
Classifier: Intended Audience :: Developers
Classifier: License :: OSI Approved :: MIT License
Classifier: Programming Language :: Python :: 3
Classifier: Programming Language :: Python :: 3.11
Classifier: Programming Language :: Python :: 3.12
Classifier: Topic :: Multimedia :: Video
Classifier: Topic :: Multimedia :: Sound/Audio :: Speech
Requires-Dist: youtube-transcript-api>=0.6.0
Requires-Dist: yt-dlp>=2023.12.30
Requires-Dist: click>=8.1.0
Requires-Dist: rich>=13.0.0
Requires-Dist: browser-cookie3>=0.19.0
Requires-Dist: tenacity>=8.2.0
Requires-Python: >=3.11
Project-URL: Homepage, https://github.com/learnerLj/readvideo
Project-URL: Issues, https://github.com/learnerLj/readvideo/issues
Project-URL: Repository, https://github.com/learnerLj/readvideo
